README.rst
setup.cfg
setup.py
src/FicusFrameworkAPI.egg-info/PKG-INFO
src/FicusFrameworkAPI.egg-info/SOURCES.txt
src/FicusFrameworkAPI.egg-info/dependency_links.txt
src/FicusFrameworkAPI.egg-info/not-zip-safe
src/FicusFrameworkAPI.egg-info/top_level.txt
src/api/IViewPortModelMapper.py
src/api/IViewPortScriptQuery.py
src/api/Page.py
src/api/__init__.py
src/api/handler/IAsyncAble.py
src/api/handler/ICacheAble.py
src/api/handler/ICacheAbleHandler.py
src/api/handler/IHandler.py
src/api/handler/IKillable.py
src/api/handler/ILogAbleHandler.py
src/api/handler/IProgressAble.py
src/api/handler/ITaskHandler.py
src/api/handler/__init__.py
src/api/handler/ce/AbstractAsyncServiceBatchCE.py
src/api/handler/ce/AbstractBatchCE.py
src/api/handler/ce/ISampleScriptCE.py
src/api/handler/ce/ISimpleScriptCE.py
src/api/handler/ce/__init__.py
src/api/handler/crawl/AbstractBatchCrawl.py
src/api/handler/crawl/AbstractSimpleCrawl.py
src/api/handler/crawl/ISampleScriptCrawl.py
src/api/handler/crawl/ISimpleScriptCrawl.py
src/api/handler/crawl/__init__.py
src/api/handler/outputer/IBaseOutputer.py
src/api/handler/outputer/IBatchOutputer.py
src/api/handler/outputer/ISimpleOutputer.py
src/api/handler/outputer/__init__.py
src/api/handler/script/ICacheAbleScript.py
src/api/handler/script/__init__.py
src/api/model/AsyncServiceRequest.py
src/api/model/BatchOutputPipe.py
src/api/model/FdInputPipe.py
src/api/model/FdInputWrapper.py
src/api/model/GraphNode.py
src/api/model/GraphRelation.py
src/api/model/OutputWrapper.py
src/api/model/ResultVO.py
src/api/model/__init__.py
src/rule_engine/RuleEngine.py
src/rule_engine/__init__.py
src/rule_engine/core/__init__.py
src/schedule/__init__.py
src/schedule/utils/__init__.py
src/schedule/utils/log/TaskLogger.py
src/schedule/utils/log/__init__.py