Metadata-Version: 1.1
Name: FicusFrameworkAPI
Version: 3.0.0
Summary: A framework for Ficus by Python3.
Home-page: https://git.sobey.com/SobeyHive/FicusFramework4Py-Api
Author: sunxiang0918
Author-email: sunxiang0918@gmail.com
License: MIT
Keywords: ficus framework python Api
Platform: UNKNOWN
Classifier: Intended Audience :: Developers
Classifier: License :: OSI Approved :: GNU Lesser General Public License v2 or later (LGPLv2+)
Classifier: Natural Language :: Chinese (Simplified)
Classifier: Programming Language :: Python :: 3.6
Classifier: Programming Language :: Python :: 3.7
